scripts/add_license_headers.py
smartmemory/__init__.py
smartmemory/__version__.py
smartmemory/clear_all.py
smartmemory/interfaces.py
smartmemory/py.typed
smartmemory/scope_provider.py
smartmemory/smart_memory.py
smartmemory/clustering/__init__.py
smartmemory/clustering/deduplicator.py
smartmemory/clustering/embedding.py
smartmemory/clustering/global_cluster.py
smartmemory/clustering/graph_aggregator.py
smartmemory/clustering/llm.py
smartmemory/configuration/__init__.py
smartmemory/configuration/environment.py
smartmemory/configuration/manager.py
smartmemory/configuration/models.py
smartmemory/configuration/validator.py
smartmemory/conversation/__init__.py
smartmemory/conversation/context.py
smartmemory/conversation/manager.py
smartmemory/conversation/session.py
smartmemory/evolution/__init__.py
smartmemory/evolution/cycle.py
smartmemory/evolution/flow.py
smartmemory/evolution/registry.py
smartmemory/evolution/utilities.py
smartmemory/extraction/__init__.py
smartmemory/extraction/extractor.py
smartmemory/extraction/models.py
smartmemory/feedback/__init__.py
smartmemory/feedback/agentic_improvement.py
smartmemory/feedback/agentic_routines.py
smartmemory/feedback/cli.py
smartmemory/feedback/manager.py
smartmemory/feedback/slack.py
smartmemory/graph/__init__.py
smartmemory/graph/base.py
smartmemory/graph/smartgraph.py
smartmemory/graph/analytics/__init__.py
smartmemory/graph/analytics/edge.py
smartmemory/graph/analytics/episodes.py
smartmemory/graph/analytics/export.py
smartmemory/graph/analytics/prune.py
smartmemory/graph/analytics/temporal.py
smartmemory/graph/backends/__init__.py
smartmemory/graph/backends/backend.py
smartmemory/graph/backends/falkordb.py
smartmemory/graph/backends/queries.py
smartmemory/graph/core/__init__.py
smartmemory/graph/core/edges.py
smartmemory/graph/core/memory_path.py
smartmemory/graph/core/nodes.py
smartmemory/graph/core/search.py
smartmemory/graph/models/__init__.py
smartmemory/graph/models/canonical_types.py
smartmemory-0.2.6.dist-info/licenses/LICENSE
smartmemory-0.2.6.dist-info/licenses/LICENSE.agpl-v3
smartmemory-0.2.6.dist-info/licenses/LICENSE.header
smartmemory-0.2.6.dist-info/METADATA
smartmemory-0.2.6.dist-info/WHEEL
smartmemory-0.2.6.dist-info/entry_points.txt
smartmemory-0.2.6.dist-info/top_level.txt
smartmemory-0.2.6.dist-info/RECORD
