Metadata-Version: 2.4
Name: smartmemory
Version: 0.2.6
Summary: Multi-layered AI memory system with graph databases, vector stores, and intelligent processing pipelines
Author: SmartMemory Team
License-Expression: AGPL-3.0-or-later
Project-URL: Homepage, https://github.com/smart-memory/smart-memory
Project-URL: Documentation, https://docs.smartmemory.ai
Project-URL: Repository, https://github.com/smart-memory/smart-memory
Project-URL: Bug Tracker, https://github.com/smart-memory/smart-memory/issues
Keywords: ai,memory,graph-database,vector-database,llm,knowledge-graph,semantic-memory,episodic-memory,rag,embeddings
Classifier: Development Status :: 4 - Beta
Classifier: Intended Audience :: Developers
Classifier: Intended Audience :: Science/Research
Classifier: Programming Language :: Python :: 3
Classifier: Programming Language :: Python :: 3.10
Classifier: Programming Language :: Python :: 3.11
Classifier: Programming Language :: Python :: 3.12
Classifier: Topic :: Scientific/Engineering :: Artificial Intelligence
Classifier: Topic :: Database
Classifier: Topic :: Software Development :: Libraries :: Python Modules
Requires-Python: >=3.10
License-File: LICENSE
License-File: LICENSE.agpl-v3
License-File: LICENSE.header
Requires-Dist: falkordb>=1.0.0
Requires-Dist: python-dateutil>=2.8.0
Requires-Dist: spacy>=3.0.0
Requires-Dist: vaderSentiment>=3.3.0
Requires-Dist: jinja2>=3.0.0
Requires-Dist: litellm>=1.0.0
Requires-Dist: openai>=1.0.0
Requires-Dist: scikit-learn>=1.0.0
Requires-Dist: pydantic>=2.0.0
Requires-Dist: redis>=4.0.0
Requires-Dist: tomli>=2.0.0; python_version < "3.11"
Requires-Dist: dspy>=3.0.0
Provides-Extra: rebel
Requires-Dist: transformers>=4.0.0; extra == "rebel"
Provides-Extra: relik
Requires-Dist: relik>=0.1.0; extra == "relik"
Provides-Extra: slack
Requires-Dist: slack-sdk>=3.0.0; extra == "slack"
Provides-Extra: aws
Requires-Dist: boto3>=1.26.0; extra == "aws"
Provides-Extra: wikipedia
Requires-Dist: wikipedia-api>=0.6.0; extra == "wikipedia"
Provides-Extra: smolagents
Requires-Dist: smolagents>=0.1.0; extra == "smolagents"
Provides-Extra: cli
Requires-Dist: click>=8.0.0; extra == "cli"
Requires-Dist: rich>=13.0.0; extra == "cli"
Requires-Dist: tabulate>=0.9.0; extra == "cli"
Provides-Extra: dev
Requires-Dist: pytest>=7.0.0; extra == "dev"
Requires-Dist: pytest-asyncio>=0.21.0; extra == "dev"
Requires-Dist: black>=23.0.0; extra == "dev"
Requires-Dist: ruff>=0.1.0; extra == "dev"
Requires-Dist: mypy>=1.0.0; extra == "dev"
Requires-Dist: build>=0.10.0; extra == "dev"
Requires-Dist: twine>=4.0.0; extra == "dev"
Provides-Extra: all
Requires-Dist: transformers>=4.0.0; extra == "all"
Requires-Dist: relik>=0.1.0; extra == "all"
Requires-Dist: slack-sdk>=3.0.0; extra == "all"
Requires-Dist: boto3>=1.26.0; extra == "all"
Requires-Dist: wikipedia-api>=0.6.0; extra == "all"
Requires-Dist: smolagents>=0.1.0; extra == "all"
Requires-Dist: click>=8.0.0; extra == "all"
Requires-Dist: rich>=13.0.0; extra == "all"
Requires-Dist: tabulate>=0.9.0; extra == "all"
Dynamic: license-file
